music21utils/__init__.py
music21utils/_nbdev.py
music21utils/core.py
music21utils-0.0.2.dist-info/LICENSE
music21utils-0.0.2.dist-info/METADATA
music21utils-0.0.2.dist-info/WHEEL
music21utils-0.0.2.dist-info/entry_points.txt
music21utils-0.0.2.dist-info/top_level.txt
music21utils-0.0.2.dist-info/RECORD
